pytafore/__init__.py
pytafore/config.py
pytafore/const.py
pytafore/db.py
pytafore/latest_schema.sql
pytafore/s3.py
pytafore/shortcuts.py
pytafore/util.py
pytafore-0.1.10.dist-info/METADATA
pytafore-0.1.10.dist-info/WHEEL
pytafore-0.1.10.dist-info/licenses/LICENSE
pytafore-0.1.10.dist-info/RECORD
