Metadata-Version: 2.4
Name: pytafore
Version: 0.1.10
Summary: V4 Data Science shared functionality
Author-email: Aaron Allen <aallen@vertafore.com>, Jen Peper <jpeper@vertafore.com>
License: Copyright (c)
License-File: LICENSE
Classifier: License :: OSI Approved :: MIT License
Classifier: Operating System :: OS Independent
Classifier: Programming Language :: Python :: 3
Requires-Python: >=3.8
Requires-Dist: awswrangler>=3.11.0
Requires-Dist: boto3>=1.34
Requires-Dist: botocore>=1.34
Requires-Dist: psycopg2-binary>=2.9
Requires-Dist: requests-aws4auth>=1.3.0
